projects/uart/uart_tx.v
`timescale 1ns / 1ps

module uart_tx(
    input clk,
    input rst_n,
    input [7:0] data,
    input data_valid,
    output data_ready,
    output uart_tx
    );

reg [9:0] counter;
reg [9:0] data_buf;
wire counter_tx;
assign data_ready = (counter == 10'd0);
assign uart_tx = data_buf[0];
assign counter_tx = (counter[5:0] == 6'd0);

always @(posedge clk or negedge rst_n) begin
    if (!rst_n) begin
        counter <= 10'b0;
        data_buf <= 10'b1;
    end else begin
        if (data_ready) begin
            if (data_valid) begin
                counter <= 10'd639;
                data_buf <= {1'b1, data, 1'b0};
            end else begin
                counter <= counter;
                data_buf <= 10'b1;
            end
        end else begin
            counter <= counter - 10'd1;
            if (counter_tx)
                data_buf <= data_buf >> 1;
            else
                data_buf <= data_buf;
        end
    end
end

endmodule

projects/uart/sim_uart_tx.v
`timescale 1ns / 1ps

module sim_uart_tx;

reg clk, rst_n;
reg [7:0] data;
reg data_valid;
wire data_ready, uart_tx;

uart_tx uart_tx_inst (
    .clk(clk),
    .rst_n(rst_n),
    .data(data),
    .data_valid(data_valid),
    .data_ready(data_ready),
    .uart_tx(uart_tx)
);

// 64x clock frequency for 115200 baudrate
always #67.817 clk = ~clk;

initial begin
    $dumpfile("sim_uart_tx.vcd");
    $dumpvars(0, sim_uart_tx);
    clk = 0;
    rst_n = 0;
    data = 0;
    data_valid = 0;
    #200 rst_n = 1;
    #10000;
    // First character A
    @(posedge clk)
    #1 data = 8'h41;
    data_valid = 1;
    // Second character B, data valid before ready 
    @(posedge clk)
    #1 data = 8'h42;
    @(posedge clk)
    wait(data_ready == 1); // Wait for data consumption
    @(posedge clk)
    #1 data_valid = 0;
    wait(data_ready == 1); // Wait for transmit finish
    #10000;
    // Third character C, data valid after ready
    @(posedge clk)
    #1 data = 8'h43;
    data_valid = 1;
    @(posedge clk)
    wait(data_ready == 1); // Wait for data consumption
    @(posedge clk)
    #1 data_valid = 0;
    wait(data_ready == 1); // Wait for transmit finish
    #10000 $finish;
end

endmodule

projects/uart/sim_uart_tx.vcd
$date
   Thu May 14 16:53:52 2026
$end

$version
  2025.1.0
  $dumpfile ("sim_uart_tx.vcd") 
$end

$timescale
  1ps
$end

$scope module sim_uart_tx $end
$var reg 1 ! clk $end
$var reg 1 " rst_n $end
$var reg 8 # data [7:0] $end
$var reg 1 $ data_valid $end
$var wire 1 % data_ready $end
$var wire 1 & uart_tx $end
$scope module uart_tx_inst $end
$var wire 1 ' clk $end
$var wire 1 ( rst_n $end
$var wire 8 ) data [7:0] $end
$var wire 1 * data_valid $end
$var wire 1 % data_ready $end
$var wire 1 & uart_tx $end
$var reg 10 + counter [9:0] $end
$var reg 10 , data_buf [9:0] $end
$var wire 1 - counter_tx $end
$upscope $end
$upscope $end
$enddefinitions $end

#0
$dumpvars
0!
0"
b0 #
0$
1%
1&
0'
0(
b0 )
0*
b0 +
b1 ,
1-
$end

#67817
1!
1'

#135634
0!
0'

#200000
1"
1(

#203451
1!
1'

#271268
0!
0'

#339085
1!
1'

#406902
0!
0'

#474719
1!
1'

#542536
0!
0'

#610353
1!
1'

#678170
0!
0'

#745987
1!
1'

#813804
0!
0'

#881621
1!
1'

#949438
0!
0'

#1017255
1!
1'

#1085072
0!
0'

#1152889
1!
1'

#1220706
0!
0'

#1288523
1!
1'

#1356340
0!
0'

#1424157
1!
1'

#1491974
0!
0'

#1559791
1!
1'

#1627608
0!
0'

#1695425
1!
1'

#1763242
0!
0'

#1831059
1!
1'

#1898876
0!
0'

#1966693
1!
1'

#2034510
0!
0'

#2102327
1!
1'

#2170144
0!
0'

#2237961
1!
1'

#2305778
0!
0'

#2373595
1!
1'

#2441412
0!
0'

#2509229
1!
1'

#2577046
0!
0'

#2644863
1!
1'

#2712680
0!
0'

#2780497
1!
1'

#2848314
0!
0'

#2916131
1!
1'

#2983948
0!
0'

#3051765
1!
1'

#3119582
0!
0'

#3187399
1!
1'

#3255216
0!
0'

#3323033
1!
1'

#3390850
0!
0'

#3458667
1!
1'

#3526484
0!
0'

#3594301
1!
1'

#3662118
0!
0'

#3729935
1!
1'

#3797752
0!
0'

#3865569
1!
1'

#3933386
0!
0'

#4001203
1!
1'

#4069020
0!
0'

#4136837
1!
1'

#4204654
0!
0'

#4272471
1!
1'

#4340288
0!
0'

#4408105
1!
1'

#4475922
0!
0'

#4543739
1!
1'

#4611556
0!
0'

#4679373
1!
1'

#4747190
0!
0'

#4815007
1!
1'

#4882824
0!
0'

#4950641
1!
1'

#5018458
0!
0'

#5086275
1!
1'

#5154092
0!
0'

#5221909
1!
1'

#5289726
0!
0'

#5357543
1!
1'

#5425360
0!
0'

#5493177
1!
1'

#5560994
0!
0'

#5628811
1!
1'

#5696628
0!
0'

#5764445
1!
1'

#5832262
0!
0'

#5900079
1!
1'

#5967896
0!
0'

#6035713
1!
1'

#6103530
0!
0'

#6171347
1!
1'

#6239164
0!
0'

#6306981
1!
1'

#6374798
0!
0'

#6442615
1!
1'

#6510432
0!
0'

#6578249
1!
1'

#6646066
0!
0'

#6713883
1!
1'

#6781700
0!
0'

#6849517
1!
1'

#6917334
0!
0'

#6985151
1!
1'

#7052968
0!
0'

#7120785
1!
1'

#7188602
0!
0'

#7256419
1!
1'

#7324236
0!
0'

#7392053
1!
1'

#7459870
0!
0'

#7527687
1!
1'

#7595504
0!
0'

#7663321
1!
1'

#7731138
0!
0'

#7798955
1!
1'

#7866772
0!
0'

#7934589
1!
1'

#8002406
0!
0'

#8070223
1!
1'

#8138040
0!
0'

#8205857
1!
1'

#8273674
0!
0'

#8341491
1!
1'

#8409308
0!
0'

#8477125
1!
1'

#8544942
0!
0'

#8612759
1!
1'

#8680576
0!
0'

#8748393
1!
1'

#8816210
0!
0'

#8884027
1!
1'

#8951844
0!
0'

#9019661
1!
1'

#9087478
0!
0'

#9155295
1!
1'

#9223112
0!
0'

#9290929
1!
1'

#9358746
0!
0'

#9426563
1!
1'

#9494380
0!
0'

#9562197
1!
1'

#9630014
0!
0'

#9697831
1!
1'

#9765648
0!
0'

#9833465
1!
1'

#9901282
0!
0'

#9969099
1!
1'

#10036916
0!
0'

#10104733
1!
1'

#10172550
0!
0'

#10240367
1!
1'

#10241367
b1000001 #
1$
b1000001 )
1*

#10308184
0!
0'

#10376001
1!
0%
0&
1'
b1001111111 +
b1010000010 ,
0-

#10377001
b1000010 #
b1000010 )

#10443818
0!
0'

#10511635
1!
1'
b1001111110 +

#10579452
0!
0'

#10647269
1!
1'
b1001111101 +

#10715086
0!
0'

#10782903
1!
1'
b1001111100 +

#10850720
0!
0'

#10918537
1!
1'
b1001111011 +

#10986354
0!
0'

#11054171
1!
1'
b1001111010 +

#11121988
0!
0'

#11189805
1!
1'
b1001111001 +

#11257622
0!
0'

#11325439
1!
1'
b1001111000 +

#11393256
0!
0'

#11461073
1!
1'
b1001110111 +

#11528890
0!
0'

#11596707
1!
1'
b1001110110 +

#11664524
0!
0'

#11732341
1!
1'
b1001110101 +

#11800158
0!
0'

#11867975
1!
1'
b1001110100 +

#11935792
0!
0'

#12003609
1!
1'
b1001110011 +

#12071426
0!
0'

#12139243
1!
1'
b1001110010 +

#12207060
0!
0'

#12274877
1!
1'
b1001110001 +

#12342694
0!
0'

#12410511
1!
1'
b1001110000 +

#12478328
0!
0'

#12546145
1!
1'
b1001101111 +

#12613962
0!
0'

#12681779
1!
1'
b1001101110 +

#12749596
0!
0'

#12817413
1!
1'
b1001101101 +

#12885230
0!
0'

#12953047
1!
1'
b1001101100 +

#13020864
0!
0'

#13088681
1!
1'
b1001101011 +

#13156498
0!
0'

#13224315
1!
1'
b1001101010 +

#13292132
0!
0'

#13359949
1!
1'
b1001101001 +

#13427766
0!
0'

#13495583
1!
1'
b1001101000 +

#13563400
0!
0'

#13631217
1!
1'
b1001100111 +

#13699034
0!
0'

#13766851
1!
1'
b1001100110 +

#13834668
0!
0'

#13902485
1!
1'
b1001100101 +

#13970302
0!
0'

#14038119
1!
1'
b1001100100 +

#14105936
0!
0'

#14173753
1!
1'
b1001100011 +

#14241570
0!
0'

#14309387
1!
1'
b1001100010 +

#14377204
0!
0'

#14445021
1!
1'
b1001100001 +

#14512838
0!
0'

#14580655
1!
1'
b1001100000 +

#14648472
0!
0'

#14716289
1!
1'
b1001011111 +

#14784106
0!
0'

#14851923
1!
1'
b1001011110 +

#14919740
0!
0'

#14987557
1!
1'
b1001011101 +

#15055374
0!
0'

#15123191
1!
1'
b1001011100 +

#15191008
0!
0'

#15258825
1!
1'
b1001011011 +

#15326642
0!
0'

#15394459
1!
1'
b1001011010 +

#15462276
0!
0'

#15530093
1!
1'
b1001011001 +

#15597910
0!
0'

#15665727
1!
1'
b1001011000 +

#15733544
0!
0'

#15801361
1!
1'
b1001010111 +

#15869178
0!
0'

#15936995
1!
1'
b1001010110 +

#16004812
0!
0'

#16072629
1!
1'
b1001010101 +

#16140446
0!
0'

#16208263
1!
1'
b1001010100 +

#16276080
0!
0'

#16343897
1!
1'
b1001010011 +

#16411714
0!
0'

#16479531
1!
1'
b1001010010 +

#16547348
0!
0'

#16615165
1!
1'
b1001010001 +

#16682982
0!
0'

#16750799
1!
1'
b1001010000 +

#16818616
0!
0'

#16886433
1!
1'
b1001001111 +

#16954250
0!
0'

#17022067
1!
1'
b1001001110 +

#17089884
0!
0'

#17157701
1!
1'
b1001001101 +

#17225518
0!
0'

#17293335
1!
1'
b1001001100 +

#17361152
0!
0'

#17428969
1!
1'
b1001001011 +

#17496786
0!
0'

#17564603
1!
1'
b1001001010 +

#17632420
0!
0'

#17700237
1!
1'
b1001001001 +

#17768054
0!
0'

#17835871
1!
1'
b1001001000 +

#17903688
0!
0'

#17971505
1!
1'
b1001000111 +

#18039322
0!
0'

#18107139
1!
1'
b1001000110 +

#18174956
0!
0'

#18242773
1!
1'
b1001000101 +

#18310590
0!
0'

#18378407
1!
1'
b1001000100 +

#18446224
0!
0'

#18514041
1!
1'
b1001000011 +

#18581858
0!
0'

#18649675
1!
1'
b1001000010 +

#18717492
0!
0'

#18785309
1!
1'
b1001000001 +

#18853126
0!
0'

#18920943
1!
1'
b1001000000 +
1-

#18988760
0!
0'

#19056577
1!
1&
1'
b1000111111 +
b101000001 ,
0-

#19124394
0!
0'

#19192211
1!
1'
b1000111110 +

#19260028
0!
0'

#19327845
1!
1'
b1000111101 +

#19395662
0!
0'

#19463479
1!
1'
b1000111100 +

#19531296
0!
0'

#19599113
1!
1'
b1000111011 +

#19666930
0!
0'

#19734747
1!
1'
b1000111010 +

#19802564
0!
0'

#19870381
1!
1'
b1000111001 +

#19938198
0!
0'

#20006015
1!
1'
b1000111000 +

#20073832
0!
0'

#20141649
1!
1'
b1000110111 +

#20209466
0!
0'

#20277283
1!
1'
b1000110110 +

#20345100
0!
0'

#20412917
1!
1'
b1000110101 +

#20480734
0!
0'

#20548551
1!
1'
b1000110100 +

#20616368
0!
0'

#20684185
1!
1'
b1000110011 +

#20752002
0!
0'

#20819819
1!
1'
b1000110010 +

#20887636
0!
0'

#20955453
1!
1'
b1000110001 +

#21023270
0!
0'

#21091087
1!
1'
b1000110000 +

#21158904
0!
0'

#21226721
1!
1'
b1000101111 +

#21294538
0!
0'

#21362355
1!
1'
b1000101110 +

#21430172
0!
0'

#21497989
1!
1'
b1000101101 +

#21565806
0!
0'

#21633623
1!
1'
b1000101100 +

#21701440
0!
0'

#21769257
1!
1'
b1000101011 +

#21837074
0!
0'

#21904891
1!
1'
b1000101010 +

#21972708
0!
0'

#22040525
1!
1'
b1000101001 +

#22108342
0!
0'

#22176159
1!
1'
b1000101000 +

#22243976
0!
0'

#22311793
1!
1'
b1000100111 +

#22379610
0!
0'

#22447427
1!
1'
b1000100110 +

#22515244
0!
0'

#22583061
1!
1'
b1000100101 +

#22650878
0!
0'

#22718695
1!
1'
b1000100100 +

#22786512
0!
0'

#22854329
1!
1'
b1000100011 +

#22922146
0!
0'

#22989963
1!
1'
b1000100010 +

#23057780
0!
0'

#23125597
1!
1'
b1000100001 +

#23193414
0!
0'

#23261231
1!
1'
b1000100000 +

#23329048
0!
0'

#23396865
1!
1'
b1000011111 +

#23464682
0!
0'

#23532499
1!
1'
b1000011110 +

#23600316
0!
0'

#23668133
1!
1'
b1000011101 +

#23735950
0!
0'

#23803767
1!
1'
b1000011100 +

#23871584
0!
0'

#23939401
1!
1'
b1000011011 +

#24007218
0!
0'

#24075035
1!
1'
b1000011010 +

#24142852
0!
0'

#24210669
1!
1'
b1000011001 +

#24278486
0!
0'

#24346303
1!
1'
b1000011000 +

#24414120
0!
0'

#24481937
1!
1'
b1000010111 +

#24549754
0!
0'

#24617571
1!
1'
b1000010110 +

#24685388
0!
0'

#24753205
1!
1'
b1000010101 +

#24821022
0!
0'

#24888839
1!
1'
b1000010100 +

#24956656
0!
0'

#25024473
1!
1'
b1000010011 +

#25092290
0!
0'

#25160107
1!
1'
b1000010010 +

#25227924
0!
0'

#25295741
1!
1'
b1000010001 +

#25363558
0!
0'

#25431375
1!
1'
b1000010000 +

#25499192
0!
0'

#25567009
1!
1'
b1000001111 +

#25634826
0!
0'

#25702643
1!
1'
b1000001110 +

#25770460
0!
0'

#25838277
1!
1'
b1000001101 +

#25906094
0!
0'

#25973911
1!
1'
b1000001100 +

#26041728
0!
0'

#26109545
1!
1'
b1000001011 +

#26177362
0!
0'

#26245179
1!
1'
b1000001010 +

#26312996
0!
0'

#26380813
1!
1'
b1000001001 +

#26448630
0!
0'

#26516447
1!
1'
b1000001000 +

#26584264
0!
0'

#26652081
1!
1'
b1000000111 +

#26719898
0!
0'

#26787715
1!
1'
b1000000110 +

#26855532
0!
0'

#26923349
1!
1'
b1000000101 +

#26991166
0!
0'

#27058983
1!
1'
b1000000100 +

#27126800
0!
0'

#27194617
1!
1'
b1000000011 +

#27262434
0!
0'

#27330251
1!
1'
b1000000010 +

#27398068
0!
0'

#27465885
1!
1'
b1000000001 +

#27533702
0!
0'

#27601519
1!
1'
b1000000000 +
1-

#27669336
0!
0'

#27737153
1!
0&
1'
b111111111 +
b10100000 ,
0-

#27804970
0!
0'

#27872787
1!
1'
b111111110 +

#27940604
0!
0'

#28008421
1!
1'
b111111101 +

#28076238
0!
0'

#28144055
1!
1'
b111111100 +

#28211872
0!
0'

#28279689
1!
1'
b111111011 +

#28347506
0!
0'

#28415323
1!
1'
b111111010 +

#28483140
0!
0'

#28550957
1!
1'
b111111001 +

#28618774
0!
0'

#28686591
1!
1'
b111111000 +

#28754408
0!
0'

#28822225
1!
1'
b111110111 +

#28890042
0!
0'

#28957859
1!
1'
b111110110 +

#29025676
0!
0'

#29093493
1!
1'
b111110101 +

#29161310
0!
0'

#29229127
1!
1'
b111110100 +

#29296944
0!
0'

#29364761
1!
1'
b111110011 +

#29432578
0!
0'

#29500395
1!
1'
b111110010 +

#29568212
0!
0'

#29636029
1!
1'
b111110001 +

#29703846
0!
0'

#29771663
1!
1'
b111110000 +

#29839480
0!
0'

#29907297
1!
1'
b111101111 +

#29975114
0!
0'

#30042931
1!
1'
b111101110 +

#30110748
0!
0'

#30178565
1!
1'
b111101101 +

#30246382
0!
0'

#30314199
1!
1'
b111101100 +

#30382016
0!
0'

#30449833
1!
1'
b111101011 +

#30517650
0!
0'

#30585467
1!
1'
b111101010 +

#30653284
0!
0'

#30721101
1!
1'
b111101001 +

#30788918
0!
0'

#30856735
1!
1'
b111101000 +

#30924552
0!
0'

#30992369
1!
1'
b111100111 +

#31060186
0!
0'

#31128003
1!
1'
b111100110 +

#31195820
0!
0'

#31263637
1!
1'
b111100101 +

#31331454
0!
0'

#31399271
1!
1'
b111100100 +

#31467088
0!
0'

#31534905
1!
1'
b111100011 +

#31602722
0!
0'

#31670539
1!
1'
b111100010 +

#31738356
0!
0'

#31806173
1!
1'
b111100001 +

#31873990
0!
0'

#31941807
1!
1'
b111100000 +

#32009624
0!
0'

#32077441
1!
1'
b111011111 +

#32145258
0!
0'

#32213075
1!
1'
b111011110 +

#32280892
0!
0'

#32348709
1!
1'
b111011101 +

#32416526
0!
0'

#32484343
1!
1'
b111011100 +

#32552160
0!
0'

#32619977
1!
1'
b111011011 +

#32687794
0!
0'

#32755611
1!
1'
b111011010 +

#32823428
0!
0'

#32891245
1!
1'
b111011001 +

#32959062
0!
0'

#33026879
1!
1'
b111011000 +

#33094696
0!
0'

#33162513
1!
1'
b111010111 +

#33230330
0!
0'

#33298147
1!
1'
b111010110 +

#33365964
0!
0'

#33433781
1!
1'
b111010101 +

#33501598
0!
0'

#33569415
1!
1'
b111010100 +

#33637232
0!
0'

#33705049
1!
1'
b111010011 +

#33772866
0!
0'

#33840683
1!
1'
b111010010 +

#33908500
0!
0'

#33976317
1!
1'
b111010001 +

#34044134
0!
0'

#34111951
1!
1'
b111010000 +

#34179768
0!
0'

#34247585
1!
1'
b111001111 +

#34315402
0!
0'

#34383219
1!
1'
b111001110 +

#34451036
0!
0'

#34518853
1!
1'
b111001101 +

#34586670
0!
0'

#34654487
1!
1'
b111001100 +

#34722304
0!
0'

#34790121
1!
1'
b111001011 +

#34857938
0!
0'

#34925755
1!
1'
b111001010 +

#34993572
0!
0'

#35061389
1!
1'
b111001001 +

#35129206
0!
0'

#35197023
1!
1'
b111001000 +

#35264840
0!
0'

#35332657
1!
1'
b111000111 +

#35400474
0!
0'

#35468291
1!
1'
b111000110 +

#35536108
0!
0'

#35603925
1!
1'
b111000101 +

#35671742
0!
0'

#35739559
1!
1'
b111000100 +

#35807376
0!
0'

#35875193
1!
1'
b111000011 +

#35943010
0!
0'

#36010827
1!
1'
b111000010 +

#36078644
0!
0'

#36146461
1!
1'
b111000001 +

#36214278
0!
0'

#36282095
1!
1'
b111000000 +
1-

#36349912
0!
0'

#36417729
1!
1'
b110111111 +
b1010000 ,
0-

#36485546
0!
0'

#36553363
1!
1'
b110111110 +

#36621180
0!
0'

#36688997
1!
1'
b110111101 +

#36756814
0!
0'

#36824631
1!
1'
b110111100 +

#36892448
0!
0'

#36960265
1!
1'
b110111011 +

#37028082
0!
0'

#37095899
1!
1'
b110111010 +

#37163716
0!
0'

#37231533
1!
1'
b110111001 +

#37299350
0!
0'

#37367167
1!
1'
b110111000 +

#37434984
0!
0'

#37502801
1!
1'
b110110111 +

#37570618
0!
0'

#37638435
1!
1'
b110110110 +

#37706252
0!
0'

#37774069
1!
1'
b110110101 +

#37841886
0!
0'

#37909703
1!
1'
b110110100 +

#37977520
0!
0'

#38045337
1!
1'
b110110011 +

#38113154
0!
0'

#38180971
1!
1'
b110110010 +

#38248788
0!
0'

#38316605
1!
1'
b110110001 +

#38384422
0!
0'

#38452239
1!
1'
b110110000 +

#38520056
0!
0'

#38587873
1!
1'
b110101111 +

#38655690
0!
0'

#38723507
1!
1'
b110101110 +

#38791324
0!
0'

#38859141
1!
1'
b110101101 +

#38926958
0!
0'

#38994775
1!
1'
b110101100 +

#39062592
0!
0'

#39130409
1!
1'
b110101011 +

#39198226
0!
0'

#39266043
1!
1'
b110101010 +

#39333860
0!
0'

#39401677
1!
1'
b110101001 +

#39469494
0!
0'

#39537311
1!
1'
b110101000 +

#39605128
0!
0'

#39672945
1!
1'
b110100111 +

#39740762
0!
0'

#39808579
1!
1'
b110100110 +

#39876396
0!
0'

#39944213
1!
1'
b110100101 +

#40012030
0!
0'

#40079847
1!
1'
b110100100 +

#40147664
0!
0'

#40215481
1!
1'
b110100011 +

#40283298
0!
0'

#40351115
1!
1'
b110100010 +

#40418932
0!
0'

#40486749
1!
1'
b110100001 +

#40554566
0!
0'

#40622383
1!
1'
b110100000 +

#40690200
0!
0'

#40758017
1!
1'
b110011111 +

#40825834
0!
0'

#40893651
1!
1'
b110011110 +

#40961468
0!
0'

#41029285
1!
1'
b110011101 +

#41097102
0!
0'

#41164919
1!
1'
b110011100 +

#41232736
0!
0'

#41300553
1!
1'
b110011011 +

#41368370
0!
0'

#41436187
1!
1'
b110011010 +

#41504004
0!
0'

#41571821
1!
1'
b110011001 +

#41639638
0!
0'

#41707455
1!
1'
b110011000 +

#41775272
0!
0'

#41843089
1!
1'
b110010111 +

#41910906
0!
0'

#41978723
1!
1'
b110010110 +

#42046540
0!
0'

#42114357
1!
1'
b110010101 +

#42182174
0!
0'

#42249991
1!
1'
b110010100 +

#42317808
0!
0'

#42385625
1!
1'
b110010011 +

#42453442
0!
0'

#42521259
1!
1'
b110010010 +

#42589076
0!
0'

#42656893
1!
1'
b110010001 +

#42724710
0!
0'

#42792527
1!
1'
b110010000 +

#42860344
0!
0'

#42928161
1!
1'
b110001111 +

#42995978
0!
0'

#43063795
1!
1'
b110001110 +

#43131612
0!
0'

#43199429
1!
1'
b110001101 +

#43267246
0!
0'

#43335063
1!
1'
b110001100 +

#43402880
0!
0'

#43470697
1!
1'
b110001011 +

#43538514
0!
0'

#43606331
1!
1'
b110001010 +

#43674148
0!
0'

#43741965
1!
1'
b110001001 +

#43809782
0!
0'

#43877599
1!
1'
b110001000 +

#43945416
0!
0'

#44013233
1!
1'
b110000111 +

#44081050
0!
0'

#44148867
1!
1'
b110000110 +

#44216684
0!
0'

#44284501
1!
1'
b110000101 +

#44352318
0!
0'

#44420135
1!
1'
b110000100 +

#44487952
0!
0'

#44555769
1!
1'
b110000011 +

#44623586
0!
0'

#44691403
1!
1'
b110000010 +

#44759220
0!
0'

#44827037
1!
1'
b110000001 +

#44894854
0!
0'

#44962671
1!
1'
b110000000 +
1-

#45030488
0!
0'

#45098305
1!
1'
b101111111 +
b101000 ,
0-

#45166122
0!
0'

#45233939
1!
1'
b101111110 +

#45301756
0!
0'

#45369573
1!
1'
b101111101 +

#45437390
0!
0'

#45505207
1!
1'
b101111100 +

#45573024
0!
0'

#45640841
1!
1'
b101111011 +

#45708658
0!
0'

#45776475
1!
1'
b101111010 +

#45844292
0!
0'

#45912109
1!
1'
b101111001 +

#45979926
0!
0'

#46047743
1!
1'
b101111000 +

#46115560
0!
0'

#46183377
1!
1'
b101110111 +

#46251194
0!
0'

#46319011
1!
1'
b101110110 +

#46386828
0!
0'

#46454645
1!
1'
b101110101 +

#46522462
0!
0'

#46590279
1!
1'
b101110100 +

#46658096
0!
0'

#46725913
1!
1'
b101110011 +

#46793730
0!
0'

#46861547
1!
1'
b101110010 +

#46929364
0!
0'

#46997181
1!
1'
b101110001 +

#47064998
0!
0'

#47132815
1!
1'
b101110000 +

#47200632
0!
0'

#47268449
1!
1'
b101101111 +

#47336266
0!
0'

#47404083
1!
1'
b101101110 +

#47471900
0!
0'

#47539717
1!
1'
b101101101 +

#47607534
0!
0'

#47675351
1!
1'
b101101100 +

#47743168
0!
0'

#47810985
1!
1'
b101101011 +

#47878802
0!
0'

#47946619
1!
1'
b101101010 +

#48014436
0!
0'

#48082253
1!
1'
b101101001 +

#48150070
0!
0'

#48217887
1!
1'
b101101000 +

#48285704
0!
0'

#48353521
1!
1'
b101100111 +

#48421338
0!
0'

#48489155
1!
1'
b101100110 +

#48556972
0!
0'

#48624789
1!
1'
b101100101 +

#48692606
0!
0'

#48760423
1!
1'
b101100100 +

#48828240
0!
0'

#48896057
1!
1'
b101100011 +

#48963874
0!
0'

#49031691
1!
1'
b101100010 +

#49099508
0!
0'

#49167325
1!
1'
b101100001 +

#49235142
0!
0'

#49302959
1!
1'
b101100000 +

#49370776
0!
0'

#49438593
1!
1'
b101011111 +

#49506410
0!
0'

#49574227
1!
1'
b101011110 +

#49642044
0!
0'

#49709861
1!
1'
b101011101 +

#49777678
0!
0'

#49845495
1!
1'
b101011100 +

#49913312
0!
0'

#49981129
1!
1'
b101011011 +

#50048946
0!
0'

#50116763
1!
1'
b101011010 +

#50184580
0!
0'

#50252397
1!
1'
b101011001 +

#50320214
0!
0'

#50388031
1!
1'
b101011000 +

#50455848
0!
0'

#50523665
1!
1'
b101010111 +

#50591482
0!
0'

#50659299
1!
1'
b101010110 +

#50727116
0!
0'

#50794933
1!
1'
b101010101 +

#50862750
0!
0'

#50930567
1!
1'
b101010100 +

#50998384
0!
0'

#51066201
1!
1'
b101010011 +

#51134018
0!
0'

#51201835
1!
1'
b101010010 +

#51269652
0!
0'

#51337469
1!
1'
b101010001 +

#51405286
0!
0'

#51473103
1!
1'
b101010000 +

#51540920
0!
0'

#51608737
1!
1'
b101001111 +

#51676554
0!
0'

#51744371
1!
1'
b101001110 +

#51812188
0!
0'

#51880005
1!
1'
b101001101 +

#51947822
0!
0'

#52015639
1!
1'
b101001100 +

#52083456
0!
0'

#52151273
1!
1'
b101001011 +

#52219090
0!
0'

#52286907
1!
1'
b101001010 +

#52354724
0!
0'

#52422541
1!
1'
b101001001 +

#52490358
0!
0'

#52558175
1!
1'
b101001000 +

#52625992
0!
0'

#52693809
1!
1'
b101000111 +

#52761626
0!
0'

#52829443
1!
1'
b101000110 +

#52897260
0!
0'

#52965077
1!
1'
b101000101 +

#53032894
0!
0'

#53100711
1!
1'
b101000100 +

#53168528
0!
0'

#53236345
1!
1'
b101000011 +

#53304162
0!
0'

#53371979
1!
1'
b101000010 +

#53439796
0!
0'

#53507613
1!
1'
b101000001 +

#53575430
0!
0'

#53643247
1!
1'
b101000000 +
1-

#53711064
0!
0'

#53778881
1!
1'
b100111111 +
b10100 ,
0-

#53846698
0!
0'

#53914515
1!
1'
b100111110 +

#53982332
0!
0'

#54050149
1!
1'
b100111101 +

#54117966
0!
0'

#54185783
1!
1'
b100111100 +

#54253600
0!
0'

#54321417
1!
1'
b100111011 +

#54389234
0!
0'

#54457051
1!
1'
b100111010 +

#54524868
0!
0'

#54592685
1!
1'
b100111001 +

#54660502
0!
0'

#54728319
1!
1'
b100111000 +

#54796136
0!
0'

#54863953
1!
1'
b100110111 +

#54931770
0!
0'

#54999587
1!
1'
b100110110 +

#55067404
0!
0'

#55135221
1!
1'
b100110101 +

#55203038
0!
0'

#55270855
1!
1'
b100110100 +

#55338672
0!
0'

#55406489
1!
1'
b100110011 +

#55474306
0!
0'

#55542123
1!
1'
b100110010 +

#55609940
0!
0'

#55677757
1!
1'
b100110001 +

#55745574
0!
0'

#55813391
1!
1'
b100110000 +

#55881208
0!
0'

#55949025
1!
1'
b100101111 +

#56016842
0!
0'

#56084659
1!
1'
b100101110 +

#56152476
0!
0'

#56220293
1!
1'
b100101101 +

#56288110
0!
0'

#56355927
1!
1'
b100101100 +

#56423744
0!
0'

#56491561
1!
1'
b100101011 +

#56559378
0!
0'

#56627195
1!
1'
b100101010 +

#56695012
0!
0'

#56762829
1!
1'
b100101001 +

#56830646
0!
0'

#56898463
1!
1'
b100101000 +

#56966280
0!
0'

#57034097
1!
1'
b100100111 +

#57101914
0!
0'

#57169731
1!
1'
b100100110 +

#57237548
0!
0'

#57305365
1!
1'
b100100101 +

#57373182
0!
0'

#57440999
1!
1'
b100100100 +

#57508816
0!
0'

#57576633
1!
1'
b100100011 +

#57644450
0!
0'

#57712267
1!
1'
b100100010 +

#57780084
0!
0'

#57847901
1!
1'
b100100001 +

#57915718
0!
0'

#57983535
1!
1'
b100100000 +

#58051352
0!
0'

#58119169
1!
1'
b100011111 +

#58186986
0!
0'

#58254803
1!
1'
b100011110 +

#58322620
0!
0'

#58390437
1!
1'
b100011101 +

#58458254
0!
0'

#58526071
1!
1'
b100011100 +

#58593888
0!
0'

#58661705
1!
1'
b100011011 +

#58729522
0!
0'

#58797339
1!
1'
b100011010 +

#58865156
0!
0'

#58932973
1!
1'
b100011001 +

#59000790
0!
0'

#59068607
1!
1'
b100011000 +

#59136424
0!
0'

#59204241
1!
1'
b100010111 +

#59272058
0!
0'

#59339875
1!
1'
b100010110 +

#59407692
0!
0'

#59475509
1!
1'
b100010101 +

#59543326
0!
0'

#59611143
1!
1'
b100010100 +

#59678960
0!
0'

#59746777
1!
1'
b100010011 +

#59814594
0!
0'

#59882411
1!
1'
b100010010 +

#59950228
0!
0'

#60018045
1!
1'
b100010001 +

#60085862
0!
0'

#60153679
1!
1'
b100010000 +

#60221496
0!
0'

#60289313
1!
1'
b100001111 +

#60357130
0!
0'

#60424947
1!
1'
b100001110 +

#60492764
0!
0'

#60560581
1!
1'
b100001101 +

#60628398
0!
0'

#60696215
1!
1'
b100001100 +

#60764032
0!
0'

#60831849
1!
1'
b100001011 +

#60899666
0!
0'

#60967483
1!
1'
b100001010 +

#61035300
0!
0'

#61103117
1!
1'
b100001001 +

#61170934
0!
0'

#61238751
1!
1'
b100001000 +

#61306568
0!
0'

#61374385
1!
1'
b100000111 +

#61442202
0!
0'

#61510019
1!
1'
b100000110 +

#61577836
0!
0'

#61645653
1!
1'
b100000101 +

#61713470
0!
0'

#61781287
1!
1'
b100000100 +

#61849104
0!
0'

#61916921
1!
1'
b100000011 +

#61984738
0!
0'

#62052555
1!
1'
b100000010 +

#62120372
0!
0'

#62188189
1!
1'
b100000001 +

#62256006
0!
0'

#62323823
1!
1'
b100000000 +
1-

#62391640
0!
0'

#62459457
1!
1'
b11111111 +
b1010 ,
0-

#62527274
0!
0'

#62595091
1!
1'
b11111110 +

#62662908
0!
0'

#62730725
1!
1'
b11111101 +

#62798542
0!
0'

#62866359
1!
1'
b11111100 +

#62934176
0!
0'

#63001993
1!
1'
b11111011 +

#63069810
0!
0'

#63137627
1!
1'
b11111010 +

#63205444
0!
0'

#63273261
1!
1'
b11111001 +

#63341078
0!
0'

#63408895
1!
1'
b11111000 +

#63476712
0!
0'

#63544529
1!
1'
b11110111 +

#63612346
0!
0'

#63680163
1!
1'
b11110110 +

#63747980
0!
0'

#63815797
1!
1'
b11110101 +

#63883614
0!
0'

#63951431
1!
1'
b11110100 +

#64019248
0!
0'

#64087065
1!
1'
b11110011 +

#64154882
0!
0'

#64222699
1!
1'
b11110010 +

#64290516
0!
0'

#64358333
1!
1'
b11110001 +

#64426150
0!
0'

#64493967
1!
1'
b11110000 +

